puz.py
puzpy-0.3.2.dist-info/licenses/LICENSE
puzpy-0.3.2.dist-info/METADATA
puzpy-0.3.2.dist-info/WHEEL
puzpy-0.3.2.dist-info/top_level.txt
puzpy-0.3.2.dist-info/RECORD
