Metadata-Version: 2.4
Name: puzpy
Version: 0.3.2
Summary: python crossword puzzle library
Author-email: Alex Dejarnatt <adejarnatt@gmail.com>
Maintainer-email: Alex Dejarnatt <adejarnatt@gmail.com>
License-Expression: MIT
Project-URL: Repository, https://github.com/alexdej/puzpy.git
Project-URL: Issues, https://github.com/alexdej/puzpy/issues
Keywords: puz,crosswords,crossword,puzzle,acrosslite,xword,xwords
Classifier: Development Status :: 5 - Production/Stable
Classifier: Intended Audience :: Developers
Classifier: Operating System :: OS Independent
Classifier: Programming Language :: Python :: 2
Classifier: Programming Language :: Python :: 2.7
Classifier: Programming Language :: Python :: 3
Classifier: Programming Language :: Python :: 3.8
Classifier: Programming Language :: Python :: 3.9
Classifier: Programming Language :: Python :: 3.10
Classifier: Programming Language :: Python :: 3.11
Classifier: Programming Language :: Python :: 3.12
Classifier: Programming Language :: Python :: 3.13
Classifier: Topic :: Games/Entertainment :: Puzzle Games
License-File: LICENSE
Dynamic: license-file
